optunafs/__init__.py
optunafs/selector.py
optunafs-0.1.0.post1.dist-info/LICENSE
optunafs-0.1.0.post1.dist-info/METADATA
optunafs-0.1.0.post1.dist-info/WHEEL
optunafs-0.1.0.post1.dist-info/top_level.txt
optunafs-0.1.0.post1.dist-info/RECORD
