Metadata-Version: 2.1
Name: optunafs
Version: 0.1.0.post1
Summary: Feature selection with Optuna optimization
Author-email: Dilge Karakas <karakasdilge@gmail.com>
License: MIT
Project-URL: Homepage, https://github.com/dilgekarakas/optunafs
Project-URL: Documentation, https://github.com/dilgekarakas/optunafs#readme
Project-URL: Repository, https://github.com/dilgekarakas/optunafs.git
Keywords: machine learning,feature selection,optuna,optimization
Classifier: Development Status :: 3 - Alpha
Classifier: Intended Audience :: Science/Research
Classifier: License :: OSI Approved :: MIT License
Classifier: Programming Language :: Python :: 3
Classifier: Programming Language :: Python :: 3.8
Classifier: Programming Language :: Python :: 3.9
Classifier: Programming Language :: Python :: 3.10
Classifier: Topic :: Scientific/Engineering :: Artificial Intelligence
Requires-Python: >=3.8
License-File: LICENSE
Requires-Dist: numpy
Requires-Dist: pandas
Requires-Dist: scikit-learn
Requires-Dist: optuna
Requires-Dist: lightgbm>=4.5.0
Provides-Extra: dev
Requires-Dist: pytest>=7.0; extra == "dev"
Requires-Dist: black>=22.0; extra == "dev"
Requires-Dist: isort>=5.0; extra == "dev"
Requires-Dist: mypy>=0.9; extra == "dev"
